{
  "保全申请书": {
    "files": [
      "保全申请书\\01_保全申请书.pdf"
    ],
    "type": "保全申请书",
    "required": true
  },
  "起诉状": {
    "files": [
      "起诉状\\起诉状.doc"
    ],
    "type": "起诉状",
    "required": true
  },
  "身份证明材料": {
    "files": [
      "身份证明材料\\03_申请人证照.pdf",
      "身份证明材料\\04_被申请人身份证.pdf",
      "身份证明材料\\05_代理人授权书.pdf"
    ],
    "type": "身份证明材料",
    "required": true
  },
  "证据材料": {
    "files": [
      "证据材料\\证据材料.doc"
    ],
    "type": "证据材料",
    "required": false
  },
  "担保材料": {
    "files": [
      "担保材料\\06_担保函.pdf",
      "担保材料\\07_保证人证照.pdf"
    ],
    "type": "担保材料",
    "required": true
  },
  "其他材料": {
    "files": [
      "其他材料\\其他材料.doc"
    ],
    "type": "其他材料",
    "required": false
  }
}